sea_dsl-0.7.3.dist-info/METADATA
sea_dsl-0.7.3.dist-info/WHEEL
sea_dsl-0.7.3.dist-info/licenses/LICENSE
sea_dsl/__init__.py
sea_dsl/sea_dsl.cpython-311-aarch64-linux-gnu.so
sea_dsl/sea_dsl.pyi
sea_dsl-0.7.3.dist-info/RECORD
