Metadata-Version: 2.4
Name: sea-dsl
Version: 0.7.3
Classifier: Development Status :: 3 - Alpha
Classifier: Intended Audience :: Developers
Classifier: License :: OSI Approved :: MIT License
Classifier: License :: OSI Approved :: Apache Software License
Classifier: Programming Language :: Python :: 3
Classifier: Programming Language :: Python :: 3.11
Classifier: Programming Language :: Python :: 3.12
Classifier: Programming Language :: Rust
Classifier: Topic :: Software Development :: Libraries
Requires-Dist: pytest>=7.4 ; extra == 'dev'
Requires-Dist: mypy>=1.0 ; extra == 'dev'
Provides-Extra: dev
License-File: LICENSE
Summary: SEA DSL - Semantic Enterprise Architecture Domain Specific Language
Keywords: enterprise-architecture,dsl,domain-modeling,business-logic
Home-Page: https://github.com/GodSpeedAI/DomainForge
Author: DomainForge Contributors
License: Apache-2.0
Requires-Python: >=3.11
